[
  {
    "id": "cert-001",
    "hostname": "switch-paris-dc-01.nttdata.com",
    "device_type": "juniper",
    "site_code": "PARIS-DC",
    "service_type": "management_https",
    "common_name": "switch-paris-dc-01.nttdata.com",
    "subject_alternative_names": ["switch-paris-dc-01.nttdata.com", "10.100.1.10"],
    "issuer": "CN=Internal-CA, O=NTT DATA, C=FR",
    "serial_number": "3a4b5c6d7e8f9a0b",
    "not_before": "2024-03-18T00:00:00Z",
    "not_after": "2025-03-18T23:59:59Z",
    "days_until_expiry": 0,
    "key_algorithm": "RSA",
    "key_size": 2048,
    "signature_algorithm": "sha256WithRSAEncryption",
    "is_self_signed": false,
    "certificate_fingerprint": "A1:B2:C3:D4:E5:F6:01:02:03:04:05:06:07:08:09:10",
    "discovered_at": "2025-03-18T02:15:30Z",
    "environment": "production"
  },
  {
    "id": "cert-002",
    "hostname": "switch-paris-dc-02.nttdata.com",
    "device_type": "ale",
    "site_code": "PARIS-DC",
    "service_type": "management_https",
    "common_name": "switch-paris-dc-02.nttdata.com",
    "subject_alternative_names": ["switch-paris-dc-02.nttdata.com"],
    "issuer": "CN=Internal-CA, O=NTT DATA, C=FR",
    "serial_number": "4b5c6d7e8f9a0b1c",
    "not_before": "2024-03-18T00:00:00Z",
    "not_after": "2025-04-25T23:59:59Z",
    "days_until_expiry": 38,
    "key_algorithm": "RSA",
    "key_size": 2048,
    "signature_algorithm": "sha256WithRSAEncryption",
    "is_self_signed": false,
    "certificate_fingerprint": "B2:C3:D4:E5:F6:01:02:03:04:05:06:07:08:09:10:11",
    "discovered_at": "2025-03-18T02:16:45Z",
    "environment": "production"
  },
  {
    "id": "cert-003",
    "hostname": "fw-brussels-01.nttdata.com",
    "device_type": "palo_alto",
    "site_code": "BRUSSELS-DC",
    "service_type": "management_https",
    "common_name": "fw-brussels-01.nttdata.com",
    "subject_alternative_names": ["fw-brussels-01.nttdata.com", "10.200.1.1"],
    "issuer": "CN=Internal-CA, O=NTT DATA, C=BE",
    "serial_number": "5c6d7e8f9a0b1c2d",
    "not_before": "2024-06-01T00:00:00Z",
    "not_after": "2025-06-01T23:59:59Z",
    "days_until_expiry": 75,
    "key_algorithm": "RSA",
    "key_size": 4096,
    "signature_algorithm": "sha256WithRSAEncryption",
    "is_self_signed": false,
    "certificate_fingerprint": "C3:D4:E5:F6:01:02:03:04:05:06:07:08:09:10:11:12",
    "discovered_at": "2025-03-18T02:17:20Z",
    "environment": "production"
  },
  {
    "id": "cert-004",
    "hostname": "lb-paris-vip-01.nttdata.com",
    "device_type": "f5",
    "site_code": "PARIS-DC",
    "service_type": "load_balancer_ssl",
    "common_name": "*.nttdata.com",
    "subject_alternative_names": ["*.nttdata.com", "nttdata.com"],
    "issuer": "CN=DigiCert SHA2 Secure Server CA, O=DigiCert Inc, C=US",
    "serial_number": "6d7e8f9a0b1c2d3e",
    "not_before": "2024-01-15T00:00:00Z",
    "not_after": "2026-01-15T23:59:59Z",
    "days_until_expiry": 303,
    "key_algorithm": "RSA",
    "key_size": 2048,
    "signature_algorithm": "sha256WithRSAEncryption",
    "is_self_signed": false,
    "certificate_fingerprint": "D4:E5:F6:01:02:03:04:05:06:07:08:09:10:11:12:13",
    "discovered_at": "2025-03-18T02:18:10Z",
    "environment": "production"
  },
  {
    "id": "cert-005",
    "hostname": "ap-paris-floor3-01.nttdata.com",
    "device_type": "juniper_mist",
    "site_code": "PARIS-OFFICE",
    "service_type": "radius_tls",
    "common_name": "radius.nttdata.com",
    "subject_alternative_names": ["radius.nttdata.com"],
    "issuer": "CN=Internal-CA, O=NTT DATA, C=FR",
    "serial_number": "7e8f9a0b1c2d3e4f",
    "not_before": "2024-09-01T00:00:00Z",
    "not_after": "2025-09-01T23:59:59Z",
    "days_until_expiry": 167,
    "key_algorithm": "RSA",
    "key_size": 2048,
    "signature_algorithm": "sha256WithRSAEncryption",
    "is_self_signed": false,
    "certificate_fingerprint": "E5:F6:01:02:03:04:05:06:07:08:09:10:11:12:13:14",
    "discovered_at": "2025-03-18T02:19:00Z",
    "environment": "production"
  },
  {
    "id": "cert-006",
    "hostname": "switch-paris-dc-03.nttdata.com",
    "device_type": "ale",
    "site_code": "PARIS-DC",
    "service_type": "management_https",
    "common_name": "switch-paris-dc-03.nttdata.com",
    "subject_alternative_names": ["switch-paris-dc-03.nttdata.com"],
    "issuer": "CN=switch-paris-dc-03.nttdata.com",
    "serial_number": "8f9a0b1c2d3e4f50",
    "not_before": "2023-03-20T00:00:00Z",
    "not_after": "2025-03-20T23:59:59Z",
    "days_until_expiry": 2,
    "key_algorithm": "RSA",
    "key_size": 1024,
    "signature_algorithm": "sha1WithRSAEncryption",
    "is_self_signed": true,
    "certificate_fingerprint": "F6:01:02:03:04:05:06:07:08:09:10:11:12:13:14:15",
    "discovered_at": "2025-03-18T02:20:15Z",
    "environment": "production"
  }
]